{
    "success": true,
    "timestamp": "2025-06-17T23:15:14.900356",
    "stock_data": {
        "symbol": "META",
        "name": "Meta Platforms, Inc.",
        "current_price": {
            "USD": 700.41,
            "INR": 60535.93,
            "EUR": 609.22,
            "BTC": 0.0067317,
            "ETH": 0.28248581
        },
        "market_cap": 1761053507584,
        "volume": 5325275,
        "pe_ratio": 27.40245,
        "dividend_yield": 30.0,
        "52_week_high": 740.91,
        "52_week_low": 442.65,
        "sector": "Communication Services",
        "industry": "Internet Content & Information"
    },
    "technical_indicators": {
        "sma_50": 607.8054541015625,
        "sma_200": 602.3833021545411,
        "ema_50": 637.679549272954,
        "rsi": 66.99551865233444,
        "bollinger_upper": 723.5575067185923,
        "bollinger_lower": 614.7263555860952,
        "macd": 23.88147054460171,
        "signal_line": 24.248173741778974,
        "macd_histogram": -0.3667031971772623,
        "volatility": 0.020690031344512007,
        "momentum": 0.19348474049486178
    },
    "sentiment_analysis": {
        "alpha_vantage": {
            "positive": 0,
            "negative": 0,
            "neutral": 0
        },
        "reddit": {
            "positive": 64,
            "negative": 61,
            "neutral": 59
        },
        "google_news": {
            "positive": 5,
            "negative": 2,
            "neutral": 3
        },
        "aggregated": {
            "positive": 69,
            "negative": 63,
            "neutral": 62
        }
    },
    "recommendation": {
        "action": "BUY",
        "buy_score": 0.06263316200630747,
        "sell_score": 0.03736683799369253,
        "explanation": "Recommendation for Meta Platforms, Inc. (META): BUY\nCurrent Price: $700.41\n\nBuy Score: 0.063, Sell Score: 0.037\n\nBullish Factors:\n- Stock is in an uptrend (50-day SMA > 200-day SMA).\n\nRisk Assessment:\n- Volatility: 0.0207 (higher values indicate higher risk)\n- Sector: Communication Services\n- Industry: Internet Content & Information\n",
        "support_level": 572.264137046814,
        "resistance_level": 735.4269470214844,
        "risk_level": "MEDIUM",
        "timeframe": "MEDIUM_TERM"
    },
    "mpt_metrics": {
        "annual_return": 0.5230079584014142,
        "annual_volatility": 0.36583089609664177,
        "sharpe_ratio": 1.3749739668476069,
        "beta": 1.4975540708357402,
        "alpha": 0.27750594139524376
    },
    "institutional_investments": {
        "top_holders": [
            {
                "name": "Vanguard Group Inc",
                "shares": 191058533,
                "date_reported": "2025-03-31 00:00:00",
                "pct_out": 0,
                "value": 133889048127
            },
            {
                "name": "Blackrock Inc.",
                "shares": 166370320,
                "date_reported": "2025-03-31 00:00:00",
                "pct_out": 0,
                "value": 116588165059
            },
            {
                "name": "FMR, LLC",
                "shares": 135174317,
                "date_reported": "2025-03-31 00:00:00",
                "pct_out": 0,
                "value": 94726785295
            },
            {
                "name": "State Street Corporation",
                "shares": 85275239,
                "date_reported": "2025-03-31 00:00:00",
                "pct_out": 0,
                "value": 59758757692
            },
            {
                "name": "JPMORGAN CHASE & CO",
                "shares": 58198195,
                "date_reported": "2025-03-31 00:00:00",
                "pct_out": 0,
                "value": 40783841521
            }
        ],
        "total_shares_held": 836400934,
        "total_value": 586128884938,
        "institutional_ownership_pct": 0.00071000005,
        "insider_ownership_pct": 0.80060995
    },
    "mutual_fund_investments": {
        "top_holders": [
            {
                "name": "VANGUARD INDEX FUNDS-Vanguard Total Stock Market Index Fund",
                "shares": 69185079,
                "date_reported": "2025-03-31 00:00:00",
                "pct_out": 0,
                "value": 48483175425
            },
            {
                "name": "VANGUARD INDEX FUNDS-Vanguard 500 Index Fund",
                "shares": 60849940,
                "date_reported": "2025-03-31 00:00:00",
                "pct_out": 0,
                "value": 42642118189
            },
            {
                "name": "Fidelity Contrafund",
                "shares": 40960591,
                "date_reported": "2025-04-30 00:00:00",
                "pct_out": 0,
                "value": 28704159158
            },
            {
                "name": "Fidelity Concord Street Trust-Fidelity 500 Index Fund",
                "shares": 27508485,
                "date_reported": "2025-04-30 00:00:00",
                "pct_out": 0,
                "value": 19277259247
            },
            {
                "name": "GROWTH FUND OF AMERICA",
                "shares": 26316013,
                "date_reported": "2025-03-31 00:00:00",
                "pct_out": 0,
                "value": 18441604652
            }
        ],
        "total_shares_held": 328405780,
        "total_value": 230138568492
    },
    "financial_statements": {
        "balance_sheet": {
            "Treasury Shares Number": {
                "2024-12-31 00:00:00": null,
                "2023-12-31 00:00:00": 0.0,
                "2022-12-31 00:00:00": null,
                "2021-12-31 00:00:00": null,
                "2020-12-31 00:00:00": null
            },
            "Ordinary Shares Number": {
                "2024-12-31 00:00:00": 2534487662.0,
                "2023-12-31 00:00:00": 2561000000.0,
                "2022-12-31 00:00:00": 2614000000.0,
                "2021-12-31 00:00:00": 2741000000.0,
                "2020-12-31 00:00:00": null
            },
            "Share Issued": {
                "2024-12-31 00:00:00": 2534487662.0,
                "2023-12-31 00:00:00": 2561000000.0,
                "2022-12-31 00:00:00": 2614000000.0,
                "2021-12-31 00:00:00": 2741000000.0,
                "2020-12-31 00:00:00": null
            },
            "Total Debt": {
                "2024-12-31 00:00:00": 49060000000.0,
                "2023-12-31 00:00:00": 37234000000.0,
                "2022-12-31 00:00:00": 26591000000.0,
                "2021-12-31 00:00:00": 13873000000.0,
                "2020-12-31 00:00:00": null
            },
            "Tangible Book Value": {
                "2024-12-31 00:00:00": 161068000000.0,
                "2023-12-31 00:00:00": 131726000000.0,
                "2022-12-31 00:00:00": 104510000000.0,
                "2021-12-31 00:00:00": 105048000000.0,
                "2020-12-31 00:00:00": null
            },
            "Invested Capital": {
                "2024-12-31 00:00:00": 211463000000.0,
                "2023-12-31 00:00:00": 171553000000.0,
                "2022-12-31 00:00:00": 135636000000.0,
                "2021-12-31 00:00:00": 124879000000.0,
                "2020-12-31 00:00:00": null
            },
            "Working Capital": {
                "2024-12-31 00:00:00": 66449000000.0,
                "2023-12-31 00:00:00": 53405000000.0,
                "2022-12-31 00:00:00": 32523000000.0,
                "2021-12-31 00:00:00": 45531000000.0,
                "2020-12-31 00:00:00": null
            },
            "Net Tangible Assets": {
                "2024-12-31 00:00:00": 161068000000.0,
                "2023-12-31 00:00:00": 131726000000.0,
                "2022-12-31 00:00:00": 104510000000.0,
                "2021-12-31 00:00:00": 105048000000.0,
                "2020-12-31 00:00:00": null
            },
            "Capital Lease Obligations": {
                "2024-12-31 00:00:00": 20234000000.0,
                "2023-12-31 00:00:00": 18849000000.0,
                "2022-12-31 00:00:00": 16668000000.0,
                "2021-12-31 00:00:00": 13873000000.0,
                "2020-12-31 00:00:00": null
            },
            "Common Stock Equity": {
                "2024-12-31 00:00:00": 182637000000.0,
                "2023-12-31 00:00:00": 153168000000.0,
                "2022-12-31 00:00:00": 125713000000.0,
                "2021-12-31 00:00:00": 124879000000.0,
                "2020-12-31 00:00:00": null
            },
            "Total Capitalization": {
                "2024-12-31 00:00:00": 211463000000.0,
                "2023-12-31 00:00:00": 171553000000.0,
                "2022-12-31 00:00:00": 135636000000.0,
                "2021-12-31 00:00:00": 124879000000.0,
                "2020-12-31 00:00:00": null
            },
            "Total Equity Gross Minority Interest": {
                "2024-12-31 00:00:00": 182637000000.0,
                "2023-12-31 00:00:00": 153168000000.0,
                "2022-12-31 00:00:00": 125713000000.0,
                "2021-12-31 00:00:00": 124879000000.0,
                "2020-12-31 00:00:00": null
            },
            "Stockholders Equity": {
                "2024-12-31 00:00:00": 182637000000.0,
                "2023-12-31 00:00:00": 153168000000.0,
                "2022-12-31 00:00:00": 125713000000.0,
                "2021-12-31 00:00:00": 124879000000.0,
                "2020-12-31 00:00:00": null
            },
            "Gains Losses Not Affecting Retained Earnings": {
                "2024-12-31 00:00:00": -3097000000.0,
                "2023-12-31 00:00:00": -2155000000.0,
                "2022-12-31 00:00:00": -3530000000.0,
                "2021-12-31 00:00:00": -693000000.0,
                "2020-12-31 00:00:00": null
            },
            "Other Equity Adjustments": {
                "2024-12-31 00:00:00": -3097000000.0,
                "2023-12-31 00:00:00": -2155000000.0,
                "2022-12-31 00:00:00": -3530000000.0,
                "2021-12-31 00:00:00": -693000000.0,
                "2020-12-31 00:00:00": null
            },
            "Retained Earnings": {
                "2024-12-31 00:00:00": 102506000000.0,
                "2023-12-31 00:00:00": 82070000000.0,
                "2022-12-31 00:00:00": 64799000000.0,
                "2021-12-31 00:00:00": 69761000000.0,
                "2020-12-31 00:00:00": null
            },
            "Additional Paid In Capital": {
                "2024-12-31 00:00:00": 83228000000.0,
                "2023-12-31 00:00:00": 73253000000.0,
                "2022-12-31 00:00:00": 64444000000.0,
                "2021-12-31 00:00:00": 55811000000.0,
                "2020-12-31 00:00:00": null
            },
            "Capital Stock": {
                "2024-12-31 00:00:00": 0.0,
                "2023-12-31 00:00:00": 0.0,
                "2022-12-31 00:00:00": 0.0,
                "2021-12-31 00:00:00": 0.0,
                "2020-12-31 00:00:00": null
            },
            "Common Stock": {
                "2024-12-31 00:00:00": 0.0,
                "2023-12-31 00:00:00": 0.0,
                "2022-12-31 00:00:00": 0.0,
                "2021-12-31 00:00:00": 0.0,
                "2020-12-31 00:00:00": null
            },
            "Total Liabilities Net Minority Interest": {
                "2024-12-31 00:00:00": 93417000000.0,
                "2023-12-31 00:00:00": 76455000000.0,
                "2022-12-31 00:00:00": 60014000000.0,
                "2021-12-31 00:00:00": 41108000000.0,
                "2020-12-31 00:00:00": null
            },
            "Total Non Current Liabilities Net Minority Interest": {
                "2024-12-31 00:00:00": 59821000000.0,
                "2023-12-31 00:00:00": 44495000000.0,
                "2022-12-31 00:00:00": 32988000000.0,
                "2021-12-31 00:00:00": 19973000000.0,
                "2020-12-31 00:00:00": null
            },
            "Other Non Current Liabilities": {
                "2024-12-31 00:00:00": 2716000000.0,
                "2023-12-31 00:00:00": 1370000000.0,
                "2022-12-31 00:00:00": 1119000000.0,
                "2021-12-31 00:00:00": 1289000000.0,
                "2020-12-31 00:00:00": null
            },
            "Tradeand Other Payables Non Current": {
                "2024-12-31 00:00:00": 9987000000.0,
                "2023-12-31 00:00:00": 7514000000.0,
                "2022-12-31 00:00:00": 6645000000.0,
                "2021-12-31 00:00:00": 5938000000.0,
                "2020-12-31 00:00:00": null
            },
            "Long Term Debt And Capital Lease Obligation": {
                "2024-12-31 00:00:00": 47118000000.0,
                "2023-12-31 00:00:00": 35611000000.0,
                "2022-12-31 00:00:00": 25224000000.0,
                "2021-12-31 00:00:00": 12746000000.0,
                "2020-12-31 00:00:00": null
            },
            "Long Term Capital Lease Obligation": {
                "2024-12-31 00:00:00": 18292000000.0,
                "2023-12-31 00:00:00": 17226000000.0,
                "2022-12-31 00:00:00": 15301000000.0,
                "2021-12-31 00:00:00": 12746000000.0,
                "2020-12-31 00:00:00": null
            },
            "Long Term Debt": {
                "2024-12-31 00:00:00": 28826000000.0,
                "2023-12-31 00:00:00": 18385000000.0,
                "2022-12-31 00:00:00": 9923000000.0,
                "2021-12-31 00:00:00": null,
                "2020-12-31 00:00:00": null
            },
            "Current Liabilities": {
                "2024-12-31 00:00:00": 33596000000.0,
                "2023-12-31 00:00:00": 31960000000.0,
                "2022-12-31 00:00:00": 27026000000.0,
                "2021-12-31 00:00:00": 21135000000.0,
                "2020-12-31 00:00:00": null
            },
            "Other Current Liabilities": {
                "2024-12-31 00:00:00": 6074000000.0,
                "2023-12-31 00:00:00": 6369000000.0,
                "2022-12-31 00:00:00": 4906000000.0,
                "2021-12-31 00:00:00": 5819000000.0,
                "2020-12-31 00:00:00": null
            },
            "Current Deferred Liabilities": {
                "2024-12-31 00:00:00": null,
                "2023-12-31 00:00:00": null,
                "2022-12-31 00:00:00": null,
                "2021-12-31 00:00:00": 561000000.0,
                "2020-12-31 00:00:00": 382000000.0
            },
            "Current Deferred Revenue": {
                "2024-12-31 00:00:00": null,
                "2023-12-31 00:00:00": null,
                "2022-12-31 00:00:00": null,
                "2021-12-31 00:00:00": 561000000.0,
                "2020-12-31 00:00:00": 382000000.0
            },
            "Current Debt And Capital Lease Obligation": {
                "2024-12-31 00:00:00": 1942000000.0,
                "2023-12-31 00:00:00": 1623000000.0,
                "2022-12-31 00:00:00": 1367000000.0,
                "2021-12-31 00:00:00": 1127000000.0,
                "2020-12-31 00:00:00": null
            },
            "Current Capital Lease Obligation": {
                "2024-12-31 00:00:00": 1942000000.0,
                "2023-12-31 00:00:00": 1623000000.0,
                "2022-12-31 00:00:00": 1367000000.0,
                "2021-12-31 00:00:00": 1127000000.0,
                "2020-12-31 00:00:00": null
            },
            "Pensionand Other Post Retirement Benefit Plans Current": {
                "2024-12-31 00:00:00": 6350000000.0,
                "2023-12-31 00:00:00": 6659000000.0,
                "2022-12-31 00:00:00": 4591000000.0,
                "2021-12-31 00:00:00": 3152000000.0,
                "2020-12-31 00:00:00": null
            },
            "Payables And Accrued Expenses": {
                "2024-12-31 00:00:00": 19230000000.0,
                "2023-12-31 00:00:00": 17309000000.0,
                "2022-12-31 00:00:00": 16162000000.0,
                "2021-12-31 00:00:00": 11037000000.0,
                "2020-12-31 00:00:00": null
            },
            "Current Accrued Expenses": {
                "2024-12-31 00:00:00": 8105000000.0,
                "2023-12-31 00:00:00": 8805000000.0,
                "2022-12-31 00:00:00": 7716000000.0,
                "2021-12-31 00:00:00": 4646000000.0,
                "2020-12-31 00:00:00": null
            },
            "Payables": {
                "2024-12-31 00:00:00": 11125000000.0,
                "2023-12-31 00:00:00": 8504000000.0,
                "2022-12-31 00:00:00": 8446000000.0,
                "2021-12-31 00:00:00": 6391000000.0,
                "2020-12-31 00:00:00": null
            },
            "Other Payable": {
                "2024-12-31 00:00:00": null,
                "2023-12-31 00:00:00": null,
                "2022-12-31 00:00:00": null,
                "2021-12-31 00:00:00": 1052000000.0,
                "2020-12-31 00:00:00": 1093000000.0
            },
            "Dueto Related Parties Current": {
                "2024-12-31 00:00:00": null,
                "2023-12-31 00:00:00": 863000000.0,
                "2022-12-31 00:00:00": 1117000000.0,
                "2021-12-31 00:00:00": 1052000000.0,
                "2020-12-31 00:00:00": 1093000000.0
            },
            "Total Tax Payable": {
                "2024-12-31 00:00:00": 3438000000.0,
                "2023-12-31 00:00:00": 3655000000.0,
                "2022-12-31 00:00:00": 2339000000.0,
                "2021-12-31 00:00:00": 1256000000.0,
                "2020-12-31 00:00:00": null
            },
            "Accounts Payable": {
                "2024-12-31 00:00:00": 7687000000.0,
                "2023-12-31 00:00:00": 4849000000.0,
                "2022-12-31 00:00:00": 4990000000.0,
                "2021-12-31 00:00:00": 4083000000.0,
                "2020-12-31 00:00:00": null
            },
            "Total Assets": {
                "2024-12-31 00:00:00": 276054000000.0,
                "2023-12-31 00:00:00": 229623000000.0,
                "2022-12-31 00:00:00": 185727000000.0,
                "2021-12-31 00:00:00": 165987000000.0,
                "2020-12-31 00:00:00": null
            },
            "Total Non Current Assets": {
                "2024-12-31 00:00:00": 176009000000.0,
                "2023-12-31 00:00:00": 144258000000.0,
                "2022-12-31 00:00:00": 126178000000.0,
                "2021-12-31 00:00:00": 99321000000.0,
                "2020-12-31 00:00:00": null
            },
            "Other Non Current Assets": {
                "2024-12-31 00:00:00": 12102000000.0,
                "2023-12-31 00:00:00": 6794000000.0,
                "2022-12-31 00:00:00": 6583000000.0,
                "2021-12-31 00:00:00": 2751000000.0,
                "2020-12-31 00:00:00": null
            },
            "Investments And Advances": {
                "2024-12-31 00:00:00": 6070000000.0,
                "2023-12-31 00:00:00": 6141000000.0,
                "2022-12-31 00:00:00": 6201000000.0,
                "2021-12-31 00:00:00": 6775000000.0,
                "2020-12-31 00:00:00": null
            },
            "Investmentin Financial Assets": {
                "2024-12-31 00:00:00": 6070000000.0,
                "2023-12-31 00:00:00": 6141000000.0,
                "2022-12-31 00:00:00": 6201000000.0,
                "2021-12-31 00:00:00": 6775000000.0,
                "2020-12-31 00:00:00": null
            },
            "Available For Sale Securities": {
                "2024-12-31 00:00:00": 6070000000.0,
                "2023-12-31 00:00:00": 6141000000.0,
                "2022-12-31 00:00:00": 6201000000.0,
                "2021-12-31 00:00:00": 6775000000.0,
                "2020-12-31 00:00:00": null
            },
            "Long Term Equity Investment": {
                "2024-12-31 00:00:00": null,
                "2023-12-31 00:00:00": null,
                "2022-12-31 00:00:00": null,
                "2021-12-31 00:00:00": 6775000000.0,
                "2020-12-31 00:00:00": 6234000000.0
            },
            "Goodwill And Other Intangible Assets": {
                "2024-12-31 00:00:00": 21569000000.0,
                "2023-12-31 00:00:00": 21442000000.0,
                "2022-12-31 00:00:00": 21203000000.0,
                "2021-12-31 00:00:00": 19831000000.0,
                "2020-12-31 00:00:00": null
            },
            "Other Intangible Assets": {
                "2024-12-31 00:00:00": 915000000.0,
                "2023-12-31 00:00:00": 788000000.0,
                "2022-12-31 00:00:00": 897000000.0,
                "2021-12-31 00:00:00": 634000000.0,
                "2020-12-31 00:00:00": null
            },
            "Goodwill": {
                "2024-12-31 00:00:00": 20654000000.0,
                "2023-12-31 00:00:00": 20654000000.0,
                "2022-12-31 00:00:00": 20306000000.0,
                "2021-12-31 00:00:00": 19197000000.0,
                "2020-12-31 00:00:00": null
            },
            "Net PPE": {
                "2024-12-31 00:00:00": 136268000000.0,
                "2023-12-31 00:00:00": 109881000000.0,
                "2022-12-31 00:00:00": 92191000000.0,
                "2021-12-31 00:00:00": 69964000000.0,
                "2020-12-31 00:00:00": null
            },
            "Accumulated Depreciation": {
                "2024-12-31 00:00:00": -43317000000.0,
                "2023-12-31 00:00:00": -33134000000.0,
                "2022-12-31 00:00:00": -24975000000.0,
                "2021-12-31 00:00:00": -20080000000.0,
                "2020-12-31 00:00:00": null
            },
            "Gross PPE": {
                "2024-12-31 00:00:00": 179585000000.0,
                "2023-12-31 00:00:00": 143015000000.0,
                "2022-12-31 00:00:00": 117166000000.0,
                "2021-12-31 00:00:00": 90044000000.0,
                "2020-12-31 00:00:00": null
            },
            "Leases": {
                "2024-12-31 00:00:00": 7293000000.0,
                "2023-12-31 00:00:00": 6972000000.0,
                "2022-12-31 00:00:00": 6522000000.0,
                "2021-12-31 00:00:00": 5795000000.0,
                "2020-12-31 00:00:00": null
            },
            "Construction In Progress": {
                "2024-12-31 00:00:00": 26802000000.0,
                "2023-12-31 00:00:00": 24269000000.0,
                "2022-12-31 00:00:00": 25052000000.0,
                "2021-12-31 00:00:00": 14687000000.0,
                "2020-12-31 00:00:00": null
            },
            "Other Properties": {
                "2024-12-31 00:00:00": 95853000000.0,
                "2023-12-31 00:00:00": 71733000000.0,
                "2022-12-31 00:00:00": 55998000000.0,
                "2021-12-31 00:00:00": 45343000000.0,
                "2020-12-31 00:00:00": null
            },
            "Machinery Furniture Equipment": {
                "2024-12-31 00:00:00": null,
                "2023-12-31 00:00:00": null,
                "2022-12-31 00:00:00": null,
                "2021-12-31 00:00:00": 25584000000.0,
                "2020-12-31 00:00:00": 20544000000.0
            },
            "Buildings And Improvements": {
                "2024-12-31 00:00:00": 47076000000.0,
                "2023-12-31 00:00:00": 37961000000.0,
                "2022-12-31 00:00:00": 27720000000.0,
                "2021-12-31 00:00:00": 22531000000.0,
                "2020-12-31 00:00:00": null
            },
            "Land And Improvements": {
                "2024-12-31 00:00:00": 2561000000.0,
                "2023-12-31 00:00:00": 2080000000.0,
                "2022-12-31 00:00:00": 1874000000.0,
                "2021-12-31 00:00:00": 1688000000.0,
                "2020-12-31 00:00:00": null
            },
            "Properties": {
                "2024-12-31 00:00:00": 0.0,
                "2023-12-31 00:00:00": 0.0,
                "2022-12-31 00:00:00": 0.0,
                "2021-12-31 00:00:00": 0.0,
                "2020-12-31 00:00:00": null
            },
            "Current Assets": {
                "2024-12-31 00:00:00": 100045000000.0,
                "2023-12-31 00:00:00": 85365000000.0,
                "2022-12-31 00:00:00": 59549000000.0,
                "2021-12-31 00:00:00": 66666000000.0,
                "2020-12-31 00:00:00": null
            },
            "Other Current Assets": {
                "2024-12-31 00:00:00": 5236000000.0,
                "2023-12-31 00:00:00": 3793000000.0,
                "2022-12-31 00:00:00": 5345000000.0,
                "2021-12-31 00:00:00": 4629000000.0,
                "2020-12-31 00:00:00": null
            },
            "Prepaid Assets": {
                "2024-12-31 00:00:00": null,
                "2023-12-31 00:00:00": null,
                "2022-12-31 00:00:00": null,
                "2021-12-31 00:00:00": 4629000000.0,
                "2020-12-31 00:00:00": 2381000000.0
            },
            "Receivables": {
                "2024-12-31 00:00:00": 16994000000.0,
                "2023-12-31 00:00:00": 16169000000.0,
                "2022-12-31 00:00:00": 13466000000.0,
                "2021-12-31 00:00:00": 14039000000.0,
                "2020-12-31 00:00:00": null
            },
            "Accounts Receivable": {
                "2024-12-31 00:00:00": 16994000000.0,
                "2023-12-31 00:00:00": 16169000000.0,
                "2022-12-31 00:00:00": 13466000000.0,
                "2021-12-31 00:00:00": 14039000000.0,
                "2020-12-31 00:00:00": null
            },
            "Allowance For Doubtful Accounts Receivable": {
                "2024-12-31 00:00:00": null,
                "2023-12-31 00:00:00": null,
                "2022-12-31 00:00:00": null,
                "2021-12-31 00:00:00": null,
                "2020-12-31 00:00:00": -114000000.0
            },
            "Gross Accounts Receivable": {
                "2024-12-31 00:00:00": null,
                "2023-12-31 00:00:00": null,
                "2022-12-31 00:00:00": null,
                "2021-12-31 00:00:00": null,
                "2020-12-31 00:00:00": 11449000000.0
            },
            "Cash Cash Equivalents And Short Term Investments": {
                "2024-12-31 00:00:00": 77815000000.0,
                "2023-12-31 00:00:00": 65403000000.0,
                "2022-12-31 00:00:00": 40738000000.0,
                "2021-12-31 00:00:00": 47998000000.0,
                "2020-12-31 00:00:00": null
            },
            "Other Short Term Investments": {
                "2024-12-31 00:00:00": 33926000000.0,
                "2023-12-31 00:00:00": 23541000000.0,
                "2022-12-31 00:00:00": 26057000000.0,
                "2021-12-31 00:00:00": 31397000000.0,
                "2020-12-31 00:00:00": null
            },
            "Cash And Cash Equivalents": {
                "2024-12-31 00:00:00": 43889000000.0,
                "2023-12-31 00:00:00": 41862000000.0,
                "2022-12-31 00:00:00": 14681000000.0,
                "2021-12-31 00:00:00": 16601000000.0,
                "2020-12-31 00:00:00": null
            },
            "Cash Equivalents": {
                "2024-12-31 00:00:00": 36671000000.0,
                "2023-12-31 00:00:00": 35597000000.0,
                "2022-12-31 00:00:00": 8505000000.0,
                "2021-12-31 00:00:00": 9293000000.0,
                "2020-12-31 00:00:00": null
            },
            "Cash Financial": {
                "2024-12-31 00:00:00": 7218000000.0,
                "2023-12-31 00:00:00": 6265000000.0,
                "2022-12-31 00:00:00": 6176000000.0,
                "2021-12-31 00:00:00": 7308000000.0,
                "2020-12-31 00:00:00": null
            }
        },
        "income_statement": {
            "Tax Effect Of Unusual Items": {
                "2024-12-31 00:00:00": -81420000.0,
                "2023-12-31 00:00:00": -64416000.0,
                "2022-12-31 00:00:00": -15795000.0,
                "2021-12-31 00:00:00": -23380000.0,
                "2020-12-31 00:00:00": null
            },
            "Tax Rate For Calcs": {
                "2024-12-31 00:00:00": 0.118,
                "2023-12-31 00:00:00": 0.176,
                "2022-12-31 00:00:00": 0.195,
                "2021-12-31 00:00:00": 0.167,
                "2020-12-31 00:00:00": null
            },
            "Normalized EBITDA": {
                "2024-12-31 00:00:00": 87566000000.0,
                "2023-12-31 00:00:00": 59418000000.0,
                "2022-12-31 00:00:00": 37771000000.0,
                "2021-12-31 00:00:00": 55414000000.0,
                "2020-12-31 00:00:00": null
            },
            "Total Unusual Items": {
                "2024-12-31 00:00:00": -690000000.0,
                "2023-12-31 00:00:00": -366000000.0,
                "2022-12-31 00:00:00": -81000000.0,
                "2021-12-31 00:00:00": -140000000.0,
                "2020-12-31 00:00:00": null
            },
            "Total Unusual Items Excluding Goodwill": {
                "2024-12-31 00:00:00": -690000000.0,
                "2023-12-31 00:00:00": -366000000.0,
                "2022-12-31 00:00:00": -81000000.0,
                "2021-12-31 00:00:00": -140000000.0,
                "2020-12-31 00:00:00": null
            },
            "Net Income From Continuing Operation Net Minority Interest": {
                "2024-12-31 00:00:00": 62360000000.0,
                "2023-12-31 00:00:00": 39098000000.0,
                "2022-12-31 00:00:00": 23200000000.0,
                "2021-12-31 00:00:00": 39370000000.0,
                "2020-12-31 00:00:00": null
            },
            "Reconciled Depreciation": {
                "2024-12-31 00:00:00": 15498000000.0,
                "2023-12-31 00:00:00": 11178000000.0,
                "2022-12-31 00:00:00": 8686000000.0,
                "2021-12-31 00:00:00": 7967000000.0,
                "2020-12-31 00:00:00": null
            },
            "Reconciled Cost Of Revenue": {
                "2024-12-31 00:00:00": 30161000000.0,
                "2023-12-31 00:00:00": 25959000000.0,
                "2022-12-31 00:00:00": 25249000000.0,
                "2021-12-31 00:00:00": 22649000000.0,
                "2020-12-31 00:00:00": null
            },
            "EBITDA": {
                "2024-12-31 00:00:00": 86876000000.0,
                "2023-12-31 00:00:00": 59052000000.0,
                "2022-12-31 00:00:00": 37690000000.0,
                "2021-12-31 00:00:00": 55274000000.0,
                "2020-12-31 00:00:00": null
            },
            "EBIT": {
                "2024-12-31 00:00:00": 71378000000.0,
                "2023-12-31 00:00:00": 47874000000.0,
                "2022-12-31 00:00:00": 29004000000.0,
                "2021-12-31 00:00:00": 47307000000.0,
                "2020-12-31 00:00:00": null
            },
            "Net Interest Income": {
                "2024-12-31 00:00:00": 1973000000.0,
                "2023-12-31 00:00:00": 1043000000.0,
                "2022-12-31 00:00:00": -44000000.0,
                "2021-12-31 00:00:00": 671000000.0,
                "2020-12-31 00:00:00": null
            },
            "Interest Expense": {
                "2024-12-31 00:00:00": 715000000.0,
                "2023-12-31 00:00:00": 446000000.0,
                "2022-12-31 00:00:00": 185000000.0,
                "2021-12-31 00:00:00": 23000000.0,
                "2020-12-31 00:00:00": null
            },
            "Interest Income": {
                "2024-12-31 00:00:00": 2517000000.0,
                "2023-12-31 00:00:00": 1639000000.0,
                "2022-12-31 00:00:00": 461000000.0,
                "2021-12-31 00:00:00": 484000000.0,
                "2020-12-31 00:00:00": null
            },
            "Normalized Income": {
                "2024-12-31 00:00:00": 62968580000.0,
                "2023-12-31 00:00:00": 39399584000.0,
                "2022-12-31 00:00:00": 23265205000.0,
                "2021-12-31 00:00:00": 39486620000.0,
                "2020-12-31 00:00:00": null
            },
            "Net Income From Continuing And Discontinued Operation": {
                "2024-12-31 00:00:00": 62360000000.0,
                "2023-12-31 00:00:00": 39098000000.0,
                "2022-12-31 00:00:00": 23200000000.0,
                "2021-12-31 00:00:00": 39370000000.0,
                "2020-12-31 00:00:00": null
            },
            "Total Expenses": {
                "2024-12-31 00:00:00": 95121000000.0,
                "2023-12-31 00:00:00": 88151000000.0,
                "2022-12-31 00:00:00": 87665000000.0,
                "2021-12-31 00:00:00": 71176000000.0,
                "2020-12-31 00:00:00": null
            },
            "Total Operating Income As Reported": {
                "2024-12-31 00:00:00": 69380000000.0,
                "2023-12-31 00:00:00": 46751000000.0,
                "2022-12-31 00:00:00": 28944000000.0,
                "2021-12-31 00:00:00": 46753000000.0,
                "2020-12-31 00:00:00": null
            },
            "Diluted Average Shares": {
                "2024-12-31 00:00:00": 2614000000.0,
                "2023-12-31 00:00:00": 2629000000.0,
                "2022-12-31 00:00:00": 2702000000.0,
                "2021-12-31 00:00:00": 2859000000.0,
                "2020-12-31 00:00:00": null
            },
            "Basic Average Shares": {
                "2024-12-31 00:00:00": 2534000000.0,
                "2023-12-31 00:00:00": 2574000000.0,
                "2022-12-31 00:00:00": 2687000000.0,
                "2021-12-31 00:00:00": 2815000000.0,
                "2020-12-31 00:00:00": null
            },
            "Diluted EPS": {
                "2024-12-31 00:00:00": 23.86,
                "2023-12-31 00:00:00": 14.87,
                "2022-12-31 00:00:00": 8.59,
                "2021-12-31 00:00:00": 13.77,
                "2020-12-31 00:00:00": null
            },
            "Basic EPS": {
                "2024-12-31 00:00:00": 24.61,
                "2023-12-31 00:00:00": 15.19,
                "2022-12-31 00:00:00": 8.63,
                "2021-12-31 00:00:00": 13.99,
                "2020-12-31 00:00:00": null
            },
            "Diluted NI Availto Com Stockholders": {
                "2024-12-31 00:00:00": 62360000000.0,
                "2023-12-31 00:00:00": 39098000000.0,
                "2022-12-31 00:00:00": 23200000000.0,
                "2021-12-31 00:00:00": 39370000000.0,
                "2020-12-31 00:00:00": null
            },
            "Net Income Common Stockholders": {
                "2024-12-31 00:00:00": 62360000000.0,
                "2023-12-31 00:00:00": 39098000000.0,
                "2022-12-31 00:00:00": 23200000000.0,
                "2021-12-31 00:00:00": 39370000000.0,
                "2020-12-31 00:00:00": null
            },
            "Otherunder Preferred Stock Dividend": {
                "2024-12-31 00:00:00": null,
                "2023-12-31 00:00:00": null,
                "2022-12-31 00:00:00": null,
                "2021-12-31 00:00:00": null,
                "2020-12-31 00:00:00": 0.0
            },
            "Net Income": {
                "2024-12-31 00:00:00": 62360000000.0,
                "2023-12-31 00:00:00": 39098000000.0,
                "2022-12-31 00:00:00": 23200000000.0,
                "2021-12-31 00:00:00": 39370000000.0,
                "2020-12-31 00:00:00": null
            },
            "Net Income Including Noncontrolling Interests": {
                "2024-12-31 00:00:00": 62360000000.0,
                "2023-12-31 00:00:00": 39098000000.0,
                "2022-12-31 00:00:00": 23200000000.0,
                "2021-12-31 00:00:00": 39370000000.0,
                "2020-12-31 00:00:00": null
            },
            "Net Income Continuous Operations": {
                "2024-12-31 00:00:00": 62360000000.0,
                "2023-12-31 00:00:00": 39098000000.0,
                "2022-12-31 00:00:00": 23200000000.0,
                "2021-12-31 00:00:00": 39370000000.0,
                "2020-12-31 00:00:00": null
            },
            "Tax Provision": {
                "2024-12-31 00:00:00": 8303000000.0,
                "2023-12-31 00:00:00": 8330000000.0,
                "2022-12-31 00:00:00": 5619000000.0,
                "2021-12-31 00:00:00": 7914000000.0,
                "2020-12-31 00:00:00": null
            },
            "Pretax Income": {
                "2024-12-31 00:00:00": 70663000000.0,
                "2023-12-31 00:00:00": 47428000000.0,
                "2022-12-31 00:00:00": 28819000000.0,
                "2021-12-31 00:00:00": 47284000000.0,
                "2020-12-31 00:00:00": null
            },
            "Other Income Expense": {
                "2024-12-31 00:00:00": -690000000.0,
                "2023-12-31 00:00:00": -366000000.0,
                "2022-12-31 00:00:00": -81000000.0,
                "2021-12-31 00:00:00": -140000000.0,
                "2020-12-31 00:00:00": null
            },
            "Other Non Operating Income Expenses": {
                "2024-12-31 00:00:00": null,
                "2023-12-31 00:00:00": null,
                "2022-12-31 00:00:00": -320000000.0,
                "2021-12-31 00:00:00": 210000000.0,
                "2020-12-31 00:00:00": -34000000.0
            },
            "Special Income Charges": {
                "2024-12-31 00:00:00": null,
                "2023-12-31 00:00:00": null,
                "2022-12-31 00:00:00": null,
                "2021-12-31 00:00:00": 0.0,
                "2020-12-31 00:00:00": 0.0
            },
            "Gain On Sale Of Security": {
                "2024-12-31 00:00:00": -690000000.0,
                "2023-12-31 00:00:00": -366000000.0,
                "2022-12-31 00:00:00": -81000000.0,
                "2021-12-31 00:00:00": -140000000.0,
                "2020-12-31 00:00:00": null
            },
            "Net Non Operating Interest Income Expense": {
                "2024-12-31 00:00:00": 1973000000.0,
                "2023-12-31 00:00:00": 1043000000.0,
                "2022-12-31 00:00:00": -44000000.0,
                "2021-12-31 00:00:00": 671000000.0,
                "2020-12-31 00:00:00": null
            },
            "Total Other Finance Cost": {
                "2024-12-31 00:00:00": -171000000.0,
                "2023-12-31 00:00:00": 150000000.0,
                "2022-12-31 00:00:00": 320000000.0,
                "2021-12-31 00:00:00": -210000000.0,
                "2020-12-31 00:00:00": null
            },
            "Interest Expense Non Operating": {
                "2024-12-31 00:00:00": 715000000.0,
                "2023-12-31 00:00:00": 446000000.0,
                "2022-12-31 00:00:00": 185000000.0,
                "2021-12-31 00:00:00": 23000000.0,
                "2020-12-31 00:00:00": null
            },
            "Interest Income Non Operating": {
                "2024-12-31 00:00:00": 2517000000.0,
                "2023-12-31 00:00:00": 1639000000.0,
                "2022-12-31 00:00:00": 461000000.0,
                "2021-12-31 00:00:00": 484000000.0,
                "2020-12-31 00:00:00": null
            },
            "Operating Income": {
                "2024-12-31 00:00:00": 69380000000.0,
                "2023-12-31 00:00:00": 46751000000.0,
                "2022-12-31 00:00:00": 28944000000.0,
                "2021-12-31 00:00:00": 46753000000.0,
                "2020-12-31 00:00:00": null
            },
            "Operating Expense": {
                "2024-12-31 00:00:00": 64960000000.0,
                "2023-12-31 00:00:00": 62192000000.0,
                "2022-12-31 00:00:00": 62416000000.0,
                "2021-12-31 00:00:00": 48527000000.0,
                "2020-12-31 00:00:00": null
            },
            "Research And Development": {
                "2024-12-31 00:00:00": 43873000000.0,
                "2023-12-31 00:00:00": 38483000000.0,
                "2022-12-31 00:00:00": 35338000000.0,
                "2021-12-31 00:00:00": 24655000000.0,
                "2020-12-31 00:00:00": null
            },
            "Selling General And Administration": {
                "2024-12-31 00:00:00": 21087000000.0,
                "2023-12-31 00:00:00": 23709000000.0,
                "2022-12-31 00:00:00": 27078000000.0,
                "2021-12-31 00:00:00": 23872000000.0,
                "2020-12-31 00:00:00": null
            },
            "Selling And Marketing Expense": {
                "2024-12-31 00:00:00": 11347000000.0,
                "2023-12-31 00:00:00": 12301000000.0,
                "2022-12-31 00:00:00": 15262000000.0,
                "2021-12-31 00:00:00": 14043000000.0,
                "2020-12-31 00:00:00": null
            },
            "General And Administrative Expense": {
                "2024-12-31 00:00:00": 9740000000.0,
                "2023-12-31 00:00:00": 11408000000.0,
                "2022-12-31 00:00:00": 11816000000.0,
                "2021-12-31 00:00:00": 9829000000.0,
                "2020-12-31 00:00:00": null
            },
            "Other Gand A": {
                "2024-12-31 00:00:00": 9740000000.0,
                "2023-12-31 00:00:00": 11408000000.0,
                "2022-12-31 00:00:00": 11816000000.0,
                "2021-12-31 00:00:00": 9829000000.0,
                "2020-12-31 00:00:00": null
            },
            "Gross Profit": {
                "2024-12-31 00:00:00": 134340000000.0,
                "2023-12-31 00:00:00": 108943000000.0,
                "2022-12-31 00:00:00": 91360000000.0,
                "2021-12-31 00:00:00": 95280000000.0,
                "2020-12-31 00:00:00": null
            },
            "Cost Of Revenue": {
                "2024-12-31 00:00:00": 30161000000.0,
                "2023-12-31 00:00:00": 25959000000.0,
                "2022-12-31 00:00:00": 25249000000.0,
                "2021-12-31 00:00:00": 22649000000.0,
                "2020-12-31 00:00:00": null
            },
            "Total Revenue": {
                "2024-12-31 00:00:00": 164501000000.0,
                "2023-12-31 00:00:00": 134902000000.0,
                "2022-12-31 00:00:00": 116609000000.0,
                "2021-12-31 00:00:00": 117929000000.0,
                "2020-12-31 00:00:00": null
            },
            "Operating Revenue": {
                "2024-12-31 00:00:00": 162779000000.0,
                "2023-12-31 00:00:00": 133844000000.0,
                "2022-12-31 00:00:00": 115801000000.0,
                "2021-12-31 00:00:00": 117208000000.0,
                "2020-12-31 00:00:00": null
            }
        },
        "cash_flow": {
            "Free Cash Flow": {
                "2024-12-31 00:00:00": 54072000000.0,
                "2023-12-31 00:00:00": 44068000000.0,
                "2022-12-31 00:00:00": 19289000000.0,
                "2021-12-31 00:00:00": 38993000000.0,
                "2020-12-31 00:00:00": null
            },
            "Repurchase Of Capital Stock": {
                "2024-12-31 00:00:00": -30125000000.0,
                "2023-12-31 00:00:00": -19774000000.0,
                "2022-12-31 00:00:00": -27956000000.0,
                "2021-12-31 00:00:00": -44537000000.0,
                "2020-12-31 00:00:00": null
            },
            "Repayment Of Debt": {
                "2024-12-31 00:00:00": -1969000000.0,
                "2023-12-31 00:00:00": -1058000000.0,
                "2022-12-31 00:00:00": -850000000.0,
                "2021-12-31 00:00:00": -677000000.0,
                "2020-12-31 00:00:00": null
            },
            "Issuance Of Debt": {
                "2024-12-31 00:00:00": 10432000000.0,
                "2023-12-31 00:00:00": 8455000000.0,
                "2022-12-31 00:00:00": 9921000000.0,
                "2021-12-31 00:00:00": 0.0,
                "2020-12-31 00:00:00": null
            },
            "Capital Expenditure": {
                "2024-12-31 00:00:00": -37256000000.0,
                "2023-12-31 00:00:00": -27045000000.0,
                "2022-12-31 00:00:00": -31186000000.0,
                "2021-12-31 00:00:00": -18690000000.0,
                "2020-12-31 00:00:00": null
            },
            "Interest Paid Supplemental Data": {
                "2024-12-31 00:00:00": 486000000.0,
                "2023-12-31 00:00:00": 448000000.0,
                "2022-12-31 00:00:00": 0.0,
                "2021-12-31 00:00:00": 0.0,
                "2020-12-31 00:00:00": null
            },
            "Income Tax Paid Supplemental Data": {
                "2024-12-31 00:00:00": 10554000000.0,
                "2023-12-31 00:00:00": 6607000000.0,
                "2022-12-31 00:00:00": 6407000000.0,
                "2021-12-31 00:00:00": 8525000000.0,
                "2020-12-31 00:00:00": null
            },
            "End Cash Position": {
                "2024-12-31 00:00:00": 45438000000.0,
                "2023-12-31 00:00:00": 42827000000.0,
                "2022-12-31 00:00:00": 15596000000.0,
                "2021-12-31 00:00:00": 16865000000.0,
                "2020-12-31 00:00:00": null
            },
            "Beginning Cash Position": {
                "2024-12-31 00:00:00": 42827000000.0,
                "2023-12-31 00:00:00": 15596000000.0,
                "2022-12-31 00:00:00": 16865000000.0,
                "2021-12-31 00:00:00": 17954000000.0,
                "2020-12-31 00:00:00": null
            },
            "Effect Of Exchange Rate Changes": {
                "2024-12-31 00:00:00": -786000000.0,
                "2023-12-31 00:00:00": 113000000.0,
                "2022-12-31 00:00:00": -638000000.0,
                "2021-12-31 00:00:00": -474000000.0,
                "2020-12-31 00:00:00": null
            },
            "Changes In Cash": {
                "2024-12-31 00:00:00": 3397000000.0,
                "2023-12-31 00:00:00": 27118000000.0,
                "2022-12-31 00:00:00": -631000000.0,
                "2021-12-31 00:00:00": -615000000.0,
                "2020-12-31 00:00:00": null
            },
            "Financing Cash Flow": {
                "2024-12-31 00:00:00": -40781000000.0,
                "2023-12-31 00:00:00": -19500000000.0,
                "2022-12-31 00:00:00": -22136000000.0,
                "2021-12-31 00:00:00": -50728000000.0,
                "2020-12-31 00:00:00": null
            },
            "Cash Flow From Continuing Financing Activities": {
                "2024-12-31 00:00:00": -40781000000.0,
                "2023-12-31 00:00:00": -19500000000.0,
                "2022-12-31 00:00:00": -22136000000.0,
                "2021-12-31 00:00:00": -50728000000.0,
                "2020-12-31 00:00:00": null
            },
            "Net Other Financing Charges": {
                "2024-12-31 00:00:00": -14047000000.0,
                "2023-12-31 00:00:00": -7123000000.0,
                "2022-12-31 00:00:00": -3251000000.0,
                "2021-12-31 00:00:00": -5514000000.0,
                "2020-12-31 00:00:00": null
            },
            "Cash Dividends Paid": {
                "2024-12-31 00:00:00": -5072000000.0,
                "2023-12-31 00:00:00": 0.0,
                "2022-12-31 00:00:00": 0.0,
                "2021-12-31 00:00:00": null,
                "2020-12-31 00:00:00": null
            },
            "Common Stock Dividend Paid": {
                "2024-12-31 00:00:00": -5072000000.0,
                "2023-12-31 00:00:00": 0.0,
                "2022-12-31 00:00:00": 0.0,
                "2021-12-31 00:00:00": null,
                "2020-12-31 00:00:00": null
            },
            "Net Common Stock Issuance": {
                "2024-12-31 00:00:00": -30125000000.0,
                "2023-12-31 00:00:00": -19774000000.0,
                "2022-12-31 00:00:00": -27956000000.0,
                "2021-12-31 00:00:00": -44537000000.0,
                "2020-12-31 00:00:00": null
            },
            "Common Stock Payments": {
                "2024-12-31 00:00:00": -30125000000.0,
                "2023-12-31 00:00:00": -19774000000.0,
                "2022-12-31 00:00:00": -27956000000.0,
                "2021-12-31 00:00:00": -44537000000.0,
                "2020-12-31 00:00:00": null
            },
            "Net Issuance Payments Of Debt": {
                "2024-12-31 00:00:00": 8463000000.0,
                "2023-12-31 00:00:00": 7397000000.0,
                "2022-12-31 00:00:00": 9071000000.0,
                "2021-12-31 00:00:00": -677000000.0,
                "2020-12-31 00:00:00": null
            },
            "Net Short Term Debt Issuance": {
                "2024-12-31 00:00:00": null,
                "2023-12-31 00:00:00": null,
                "2022-12-31 00:00:00": null,
                "2021-12-31 00:00:00": 14000000.0,
                "2020-12-31 00:00:00": 24000000.0
            },
            "Net Long Term Debt Issuance": {
                "2024-12-31 00:00:00": 8463000000.0,
                "2023-12-31 00:00:00": 7397000000.0,
                "2022-12-31 00:00:00": 9071000000.0,
                "2021-12-31 00:00:00": -677000000.0,
                "2020-12-31 00:00:00": null
            },
            "Long Term Debt Payments": {
                "2024-12-31 00:00:00": -1969000000.0,
                "2023-12-31 00:00:00": -1058000000.0,
                "2022-12-31 00:00:00": -850000000.0,
                "2021-12-31 00:00:00": -677000000.0,
                "2020-12-31 00:00:00": null
            },
            "Long Term Debt Issuance": {
                "2024-12-31 00:00:00": 10432000000.0,
                "2023-12-31 00:00:00": 8455000000.0,
                "2022-12-31 00:00:00": 9921000000.0,
                "2021-12-31 00:00:00": 0.0,
                "2020-12-31 00:00:00": null
            },
            "Investing Cash Flow": {
                "2024-12-31 00:00:00": -47150000000.0,
                "2023-12-31 00:00:00": -24495000000.0,
                "2022-12-31 00:00:00": -28970000000.0,
                "2021-12-31 00:00:00": -7570000000.0,
                "2020-12-31 00:00:00": null
            },
            "Cash Flow From Continuing Investing Activities": {
                "2024-12-31 00:00:00": -47150000000.0,
                "2023-12-31 00:00:00": -24495000000.0,
                "2022-12-31 00:00:00": -28970000000.0,
                "2021-12-31 00:00:00": -7570000000.0,
                "2020-12-31 00:00:00": null
            },
            "Net Other Investing Changes": {
                "2024-12-31 00:00:00": 129000000.0,
                "2023-12-31 00:00:00": -23000000.0,
                "2022-12-31 00:00:00": -4000000.0,
                "2021-12-31 00:00:00": -331000000.0,
                "2020-12-31 00:00:00": null
            },
            "Net Investment Purchase And Sale": {
                "2024-12-31 00:00:00": -9753000000.0,
                "2023-12-31 00:00:00": 3202000000.0,
                "2022-12-31 00:00:00": 3532000000.0,
                "2021-12-31 00:00:00": 12179000000.0,
                "2020-12-31 00:00:00": null
            },
            "Sale Of Investment": {
                "2024-12-31 00:00:00": 15789000000.0,
                "2023-12-31 00:00:00": 6184000000.0,
                "2022-12-31 00:00:00": 13158000000.0,
                "2021-12-31 00:00:00": 42586000000.0,
                "2020-12-31 00:00:00": null
            },
            "Purchase Of Investment": {
                "2024-12-31 00:00:00": -25542000000.0,
                "2023-12-31 00:00:00": -2982000000.0,
                "2022-12-31 00:00:00": -9626000000.0,
                "2021-12-31 00:00:00": -30407000000.0,
                "2020-12-31 00:00:00": null
            },
            "Net Business Purchase And Sale": {
                "2024-12-31 00:00:00": -270000000.0,
                "2023-12-31 00:00:00": -629000000.0,
                "2022-12-31 00:00:00": -1312000000.0,
                "2021-12-31 00:00:00": -851000000.0,
                "2020-12-31 00:00:00": null
            },
            "Purchase Of Business": {
                "2024-12-31 00:00:00": -270000000.0,
                "2023-12-31 00:00:00": -629000000.0,
                "2022-12-31 00:00:00": -1312000000.0,
                "2021-12-31 00:00:00": -851000000.0,
                "2020-12-31 00:00:00": null
            },
            "Net PPE Purchase And Sale": {
                "2024-12-31 00:00:00": -37256000000.0,
                "2023-12-31 00:00:00": -27045000000.0,
                "2022-12-31 00:00:00": -31186000000.0,
                "2021-12-31 00:00:00": -18567000000.0,
                "2020-12-31 00:00:00": null
            },
            "Sale Of PPE": {
                "2024-12-31 00:00:00": null,
                "2023-12-31 00:00:00": 221000000.0,
                "2022-12-31 00:00:00": 245000000.0,
                "2021-12-31 00:00:00": 123000000.0,
                "2020-12-31 00:00:00": 48000000.0
            },
            "Purchase Of PPE": {
                "2024-12-31 00:00:00": -37256000000.0,
                "2023-12-31 00:00:00": -27045000000.0,
                "2022-12-31 00:00:00": -31186000000.0,
                "2021-12-31 00:00:00": -18690000000.0,
                "2020-12-31 00:00:00": null
            },
            "Operating Cash Flow": {
                "2024-12-31 00:00:00": 91328000000.0,
                "2023-12-31 00:00:00": 71113000000.0,
                "2022-12-31 00:00:00": 50475000000.0,
                "2021-12-31 00:00:00": 57683000000.0,
                "2020-12-31 00:00:00": null
            },
            "Cash Flow From Continuing Operating Activities": {
                "2024-12-31 00:00:00": 91328000000.0,
                "2023-12-31 00:00:00": 71113000000.0,
                "2022-12-31 00:00:00": 50475000000.0,
                "2021-12-31 00:00:00": 57683000000.0,
                "2020-12-31 00:00:00": null
            },
            "Change In Working Capital": {
                "2024-12-31 00:00:00": 1048000000.0,
                "2023-12-31 00:00:00": 3836000000.0,
                "2022-12-31 00:00:00": 5683000000.0,
                "2021-12-31 00:00:00": 700000000.0,
                "2020-12-31 00:00:00": null
            },
            "Change In Other Working Capital": {
                "2024-12-31 00:00:00": null,
                "2023-12-31 00:00:00": null,
                "2022-12-31 00:00:00": null,
                "2021-12-31 00:00:00": 187000000.0,
                "2020-12-31 00:00:00": 108000000.0
            },
            "Change In Other Current Liabilities": {
                "2024-12-31 00:00:00": 2805000000.0,
                "2023-12-31 00:00:00": 624000000.0,
                "2022-12-31 00:00:00": 886000000.0,
                "2021-12-31 00:00:00": 941000000.0,
                "2020-12-31 00:00:00": null
            },
            "Change In Other Current Assets": {
                "2024-12-31 00:00:00": -270000000.0,
                "2023-12-31 00:00:00": -80000000.0,
                "2022-12-31 00:00:00": -106000000.0,
                "2021-12-31 00:00:00": -349000000.0,
                "2020-12-31 00:00:00": null
            },
            "Change In Payables And Accrued Expense": {
                "2024-12-31 00:00:00": 696000000.0,
                "2023-12-31 00:00:00": 5132000000.0,
                "2022-12-31 00:00:00": 4510000000.0,
                "2021-12-31 00:00:00": 4968000000.0,
                "2020-12-31 00:00:00": null
            },
            "Change In Accrued Expense": {
                "2024-12-31 00:00:00": 323000000.0,
                "2023-12-31 00:00:00": 5081000000.0,
                "2022-12-31 00:00:00": 4300000000.0,
                "2021-12-31 00:00:00": 3544000000.0,
                "2020-12-31 00:00:00": null
            },
            "Change In Payable": {
                "2024-12-31 00:00:00": 373000000.0,
                "2023-12-31 00:00:00": 51000000.0,
                "2022-12-31 00:00:00": 210000000.0,
                "2021-12-31 00:00:00": 1424000000.0,
                "2020-12-31 00:00:00": null
            },
            "Change In Account Payable": {
                "2024-12-31 00:00:00": 373000000.0,
                "2023-12-31 00:00:00": 51000000.0,
                "2022-12-31 00:00:00": 210000000.0,
                "2021-12-31 00:00:00": 1436000000.0,
                "2020-12-31 00:00:00": null
            },
            "Change In Prepaid Assets": {
                "2024-12-31 00:00:00": -698000000.0,
                "2023-12-31 00:00:00": 559000000.0,
                "2022-12-31 00:00:00": 162000000.0,
                "2021-12-31 00:00:00": -1750000000.0,
                "2020-12-31 00:00:00": null
            },
            "Change In Receivables": {
                "2024-12-31 00:00:00": -1485000000.0,
                "2023-12-31 00:00:00": -2399000000.0,
                "2022-12-31 00:00:00": 231000000.0,
                "2021-12-31 00:00:00": -3110000000.0,
                "2020-12-31 00:00:00": null
            },
            "Changes In Account Receivables": {
                "2024-12-31 00:00:00": -1485000000.0,
                "2023-12-31 00:00:00": -2399000000.0,
                "2022-12-31 00:00:00": 231000000.0,
                "2021-12-31 00:00:00": -3110000000.0,
                "2020-12-31 00:00:00": null
            },
            "Other Non Cash Items": {
                "2024-12-31 00:00:00": 87000000.0,
                "2023-12-31 00:00:00": 411000000.0,
                "2022-12-31 00:00:00": 1982000000.0,
                "2021-12-31 00:00:00": -127000000.0,
                "2020-12-31 00:00:00": null
            },
            "Stock Based Compensation": {
                "2024-12-31 00:00:00": 16690000000.0,
                "2023-12-31 00:00:00": 14027000000.0,
                "2022-12-31 00:00:00": 11992000000.0,
                "2021-12-31 00:00:00": 9164000000.0,
                "2020-12-31 00:00:00": null
            },
            "Unrealized Gain Loss On Investment Securities": {
                "2024-12-31 00:00:00": null,
                "2023-12-31 00:00:00": null,
                "2022-12-31 00:00:00": 463000000.0,
                "2021-12-31 00:00:00": -232000000.0,
                "2020-12-31 00:00:00": 33000000.0
            },
            "Asset Impairment Charge": {
                "2024-12-31 00:00:00": 383000000.0,
                "2023-12-31 00:00:00": 2432000000.0,
                "2022-12-31 00:00:00": 2218000000.0,
                "2021-12-31 00:00:00": 0.0,
                "2020-12-31 00:00:00": null
            },
            "Deferred Tax": {
                "2024-12-31 00:00:00": -4738000000.0,
                "2023-12-31 00:00:00": 131000000.0,
                "2022-12-31 00:00:00": -3286000000.0,
                "2021-12-31 00:00:00": 609000000.0,
                "2020-12-31 00:00:00": null
            },
            "Deferred Income Tax": {
                "2024-12-31 00:00:00": -4738000000.0,
                "2023-12-31 00:00:00": 131000000.0,
                "2022-12-31 00:00:00": -3286000000.0,
                "2021-12-31 00:00:00": 609000000.0,
                "2020-12-31 00:00:00": null
            },
            "Depreciation Amortization Depletion": {
                "2024-12-31 00:00:00": 15498000000.0,
                "2023-12-31 00:00:00": 11178000000.0,
                "2022-12-31 00:00:00": 8686000000.0,
                "2021-12-31 00:00:00": 7967000000.0,
                "2020-12-31 00:00:00": null
            },
            "Depreciation And Amortization": {
                "2024-12-31 00:00:00": 15498000000.0,
                "2023-12-31 00:00:00": 11178000000.0,
                "2022-12-31 00:00:00": 8686000000.0,
                "2021-12-31 00:00:00": 7967000000.0,
                "2020-12-31 00:00:00": null
            },
            "Net Income From Continuing Operations": {
                "2024-12-31 00:00:00": 62360000000.0,
                "2023-12-31 00:00:00": 39098000000.0,
                "2022-12-31 00:00:00": 23200000000.0,
                "2021-12-31 00:00:00": 39370000000.0,
                "2020-12-31 00:00:00": null
            }
        }
    },
    "ml_analysis": {
        "success": true,
        "predicted_price": 227.9728546142578,
        "prediction_confidence": -0.6007560522038178,
        "ml_metrics": {
            "Random Forest": {
                "mse": 2178.119110630436,
                "mae": 27.331984620944198,
                "r2": 0.5889038191365732
            },
            "Gradient Boosting": {
                "mse": 2702.4284282147687,
                "mae": 31.91127111021213,
                "r2": 0.489946164801663
            },
            "XGBoost": {
                "mse": 1460.8363240586102,
                "mae": 27.909380401949466,
                "r2": 0.7242831070366762
            },
            "Stacking Ensemble": {
                "mse": 8481.317781740201,
                "mae": 67.6557450921332,
                "r2": -0.6007560522038178
            }
        },
        "optimized_rf_prediction": 319.6727574571554,
        "rl_results": {
            "success": true,
            "recommendation": "HOLD",
            "performance_pct": -0.6029687845385342,
            "final_net_worth": 9939.703121546147,
            "average_reward": 12078849.37244394,
            "average_events_per_episode": 300.79,
            "actions_distribution": {
                "hold": 0.9401197604790419,
                "buy": 0.02927478376580173,
                "sell": 0.030605455755156354
            },
            "epoch_logs": [
                {
                    "episode": 10,
                    "total_reward": 14176970.47256959,
                    "average_reward": 11230414.084337253,
                    "events_triggered": 307
                },
                {
                    "episode": 20,
                    "total_reward": 4171540.645374172,
                    "average_reward": 6333903.240874491,
                    "events_triggered": 313
                },
                {
                    "episode": 30,
                    "total_reward": 4147391.0902284808,
                    "average_reward": 9348830.746017184,
                    "events_triggered": 294
                },
                {
                    "episode": 40,
                    "total_reward": 11281458.210502358,
                    "average_reward": 13571476.16617236,
                    "events_triggered": 270
                },
                {
                    "episode": 50,
                    "total_reward": 23923816.36294027,
                    "average_reward": 12128019.906632062,
                    "events_triggered": 298
                },
                {
                    "episode": 60,
                    "total_reward": 44833419.76894965,
                    "average_reward": 17737848.534607686,
                    "events_triggered": 299
                },
                {
                    "episode": 70,
                    "total_reward": 933082.0107218586,
                    "average_reward": 10813065.29564227,
                    "events_triggered": 305
                },
                {
                    "episode": 80,
                    "total_reward": 9651206.240489818,
                    "average_reward": 12616520.901048403,
                    "events_triggered": 304
                },
                {
                    "episode": 90,
                    "total_reward": 7977337.7344646305,
                    "average_reward": 17259362.80703304,
                    "events_triggered": 295
                },
                {
                    "episode": 100,
                    "total_reward": 31370348.78728762,
                    "average_reward": 9749052.042074624,
                    "events_triggered": 291
                }
            ]
        },
        "adversarial_training_results": {
            "lstm_metrics": {
                "mse": 239232.4375,
                "r2": -45.441734313964844,
                "adv_mse": 239232.4375,
                "adv_r2": -45.441734313964844
            },
            "transformer_metrics": {
                "mse": 2981.126953125,
                "r2": 0.42127954959869385,
                "adv_mse": 4604.228515625,
                "adv_r2": 0.10618990659713745
            },
            "lstm_epoch_logs": {
                "Epoch_10": 165189.4091796875,
                "Epoch_20": 148506.111328125,
                "Epoch_30": 134621.19555664062,
                "Epoch_40": 123205.85668945312,
                "Epoch_50": 113629.79711914062
            },
            "transformer_epoch_logs": {
                "Epoch_10": 20894.133209228516,
                "Epoch_20": 3230.104690551758,
                "Epoch_30": 1862.5990200042725,
                "Epoch_40": 1334.7912273406982,
                "Epoch_50": 1531.6022624969482
            }
        }
    }
}